README.rst
setup.py
verktyg_server/__init__.py
verktyg_server/argparse.py
verktyg_server/sslutils.py
verktyg_server/testing.py
verktyg_server.egg-info/PKG-INFO
verktyg_server.egg-info/SOURCES.txt
verktyg_server.egg-info/dependency_links.txt
verktyg_server.egg-info/entry_points.txt
verktyg_server.egg-info/requires.txt
verktyg_server.egg-info/top_level.txt
verktyg_server/tests/__init__.py
verktyg_server/tests/test_argparse.py
verktyg_server/tests/test_serving.py
verktyg_server/tests/test_sockets.py
verktyg_server/tests/test_ssl.py
verktyg_server/tests/test_testing.py